mydemopkg
