Metadata-Version: 1.2
Name: mydemopkg
Version: 0.4
Summary: Printing text
Home-page: https://github.com/gangulymadhura/mydemopkg
Author: Madhura Ganguly
Author-email: gangulym23@gmail.com
License: MIT
Download-URL: https://github.com/gangulymadhura/mydemopkg/archive/refs/tags/v0.4.tar.gz
Platform: UNKNOWN
Requires-Python: >=3.5
